{
    "Name": "NAOP_CustomMechsNParts",
    "Enabled": true,

    "Version": "0.7",
    "Description": "Custom quirks, components and Mechs by NewAgeOfPower. Special thanks to the RogueTech team. Requires RogueTech.",
    "Author": "NewAgeOfPower",
    "Editor": "Harkonnen",
    "Website": "",
    "Contact": "",
	
	"DependsOn": [ "RogueTech Core", "CustomComponents", "MechEngineer", "Custom Ammo Categories", "CustomActivatableEquipment"],
	"ConflictsWith": [],
       "DataAddendumEntries":[
                {
            "name":"BattleTech.AmmoCategoryEnumeration",
            "path":"AmmoCategory.json"
        }
    ],

    "Manifest": [
			{ "Type": "WeaponDef", "Path": "weapon" },
			{ "Type": "MechDef", "Path": "mech" },
			{ "Type": "ChassisDef", "Path": "chassis" },
			{ "Type": "UpgradeDef", "Path": "actuators" },
			{ "Type": "UpgradeDef", "Path": "internals" },
			{ "Type": "UpgradeDef", "Path": "cockpits" },
			{ "Type": "UpgradeDef", "Path": "gyro" },
			{ "Type": "AmmunitionDef", "Path": "ammunition" },
			{ "Type": "AmmunitionBoxDef", "Path": "ammo" },
			{ "Type": "WeaponDef","Path": "quirks/weapon/" },
			{ "Type": "UpgradeDef","Path": "quirks/upgrade/" },
			{ "Type": "UpgradeDef","Path": "quirks/support/" },
			{ "Type": "HeatSinkDef", "Path": "engine_parts" },
			{ "Type": "HeatSinkDef","Path": "quirks/heatsink/" },
			{ "Type": "HeatSinkDef", "Path": "quirks/engine_parts" },
			{ "Type": "JumpJetDef", "Path": "quirks/jumpjet/" },
			{ "Type": "Sprite", "Path": "portrait" },
			{ "Type": "MEBonusDescriptions", "Path": "bonusDescriptions" }
    ]
	
}